[
    {
        "input": {
            "5": [
                "#minecraft:planks"
            ],
            "6": [
                "#minecraft:planks"
            ],
            "9": [
                "#minecraft:planks"
            ],
            "10": [
                "#minecraft:planks"
            ],
            "1": [
                "minecraft/iron_ingot"
            ],
            "2": [
                "minecraft/iron_ingot"
            ]
        },
        "output": {
            "id": "minecraft/smithing_table",
            "count": 1
        }
    },
    {
        "input": {
            "1": [
                "#c:ingots/iron"
            ],
            "2": [
                "#c:ingots/iron"
            ],
            "5": [
                "#aether:planks_crafting"
            ],
            "6": [
                "#aether:planks_crafting"
            ],
            "9": [
                "#aether:planks_crafting"
            ],
            "10": [
                "#aether:planks_crafting"
            ]
        },
        "output": {
            "id": "minecraft/smithing_table",
            "count": 1
        }
    }
]